aicsimageprocessing/__init__.py
aicsimageprocessing/alignMajor.py
aicsimageprocessing/backgroundCrop.py
aicsimageprocessing/backgroundSub.py
aicsimageprocessing/crop_img.py
aicsimageprocessing/diagnosticsheet.py
aicsimageprocessing/flip.py
aicsimageprocessing/imgCenter.py
aicsimageprocessing/imgToCoords.py
aicsimageprocessing/imgToProjection.py
aicsimageprocessing/imshow.py
aicsimageprocessing/isosurfaceGenerator.py
aicsimageprocessing/normalization.py
aicsimageprocessing/resize.py
aicsimageprocessing/rigidAlignment.py
aicsimageprocessing/sdfGenerator.py
aicsimageprocessing/textureAtlas.py
aicsimageprocessing/thumbnailGenerator.py
aicsimageprocessing/transformation.py
aicsimageprocessing/bin/__init__.py
aicsimageprocessing/bin/make_atlas.py
aicsimageprocessing/bin/make_thumbnail.py
aicsimageprocessing/segmentation/__init__.py
aicsimageprocessing/segmentation/nucleusSegmentation.py
aicsimageprocessing-0.8.3.dist-info/LICENSE
aicsimageprocessing-0.8.3.dist-info/METADATA
aicsimageprocessing-0.8.3.dist-info/WHEEL
aicsimageprocessing-0.8.3.dist-info/entry_points.txt
aicsimageprocessing-0.8.3.dist-info/top_level.txt
aicsimageprocessing-0.8.3.dist-info/RECORD
