Metadata-Version: 2.1
Name: aicsimageprocessing
Version: 0.8.3
Summary: A generalized scientific image processing module from the Allen Institute for Cell Science.
Home-page: https://github.com/AllenCellModeling/aicsimageprocessing
Author: AICS
Author-email: !AICS_SW@alleninstitute.org
License: Allen Institute Software License
Keywords: aicsimageprocessing
Platform: UNKNOWN
Classifier: Development Status :: 4 - Beta
Classifier: License :: Free for non-commercial use
Classifier: Natural Language :: English
Classifier: Programming Language :: Python :: 3.7
Classifier: Programming Language :: Python :: 3.8
Classifier: Programming Language :: Python :: 3.9
Classifier: Operating System :: POSIX :: Linux
Classifier: Operating System :: MacOS
Classifier: Topic :: Scientific/Engineering :: Bio-Informatics
Requires-Python: >=3.7
Requires-Dist: aicsimageio[all] (>=4.1.0)
Requires-Dist: matplotlib (>=3.1.1)
Requires-Dist: numpy (>=1.16.4)
Requires-Dist: Pillow (>=5.2.0)
Requires-Dist: PyMCubes
Requires-Dist: scikit-image (>=0.15.0)
Requires-Dist: scikit-learn
Requires-Dist: scikit-fmm (>=2021.7.8)
Requires-Dist: scipy (>=1.3.0)
Requires-Dist: vtk
Requires-Dist: aics-dask-utils
Requires-Dist: ome-zarr
Requires-Dist: universal-pathlib (==0.0.19)
Provides-Extra: all
Requires-Dist: aicsimageio[all] (>=4.1.0) ; extra == 'all'
Requires-Dist: matplotlib (>=3.1.1) ; extra == 'all'
Requires-Dist: numpy (>=1.16.4) ; extra == 'all'
Requires-Dist: Pillow (>=5.2.0) ; extra == 'all'
Requires-Dist: PyMCubes ; extra == 'all'
Requires-Dist: scikit-image (>=0.15.0) ; extra == 'all'
Requires-Dist: scikit-learn ; extra == 'all'
Requires-Dist: scikit-fmm (>=2021.7.8) ; extra == 'all'
Requires-Dist: scipy (>=1.3.0) ; extra == 'all'
Requires-Dist: vtk ; extra == 'all'
Requires-Dist: aics-dask-utils ; extra == 'all'
Requires-Dist: ome-zarr ; extra == 'all'
Requires-Dist: universal-pathlib (==0.0.19) ; extra == 'all'
Requires-Dist: codecov ; extra == 'all'
Requires-Dist: flake8 ; extra == 'all'
Requires-Dist: black ; extra == 'all'
Requires-Dist: pytest ; extra == 'all'
Requires-Dist: pytest-cov ; extra == 'all'
Requires-Dist: pytest-raises ; extra == 'all'
Requires-Dist: pytest-runner ; extra == 'all'
Requires-Dist: black (==19.10b0) ; extra == 'all'
Requires-Dist: bumpversion (>=0.5.3) ; extra == 'all'
Requires-Dist: coverage (>=5.0a4) ; extra == 'all'
Requires-Dist: flake8 (>=3.7.7) ; extra == 'all'
Requires-Dist: ipython (>=7.5.0) ; extra == 'all'
Requires-Dist: m2r (>=0.2.1) ; extra == 'all'
Requires-Dist: pytest (>=4.3.0) ; extra == 'all'
Requires-Dist: pytest-cov (==2.6.1) ; extra == 'all'
Requires-Dist: pytest-raises (>=0.10) ; extra == 'all'
Requires-Dist: pytest-runner (>=4.4) ; extra == 'all'
Requires-Dist: Sphinx (<3,>=2.0.0b1) ; extra == 'all'
Requires-Dist: sphinx-rtd-theme (>=0.4.3) ; extra == 'all'
Requires-Dist: tox (>=3.5.2) ; extra == 'all'
Requires-Dist: twine (>=1.13.0) ; extra == 'all'
Requires-Dist: wheel (>=0.33.1) ; extra == 'all'
Requires-Dist: altair ; extra == 'all'
Requires-Dist: jupyterlab ; extra == 'all'
Requires-Dist: matplotlib ; extra == 'all'
Provides-Extra: dev
Requires-Dist: black (==19.10b0) ; extra == 'dev'
Requires-Dist: bumpversion (>=0.5.3) ; extra == 'dev'
Requires-Dist: coverage (>=5.0a4) ; extra == 'dev'
Requires-Dist: flake8 (>=3.7.7) ; extra == 'dev'
Requires-Dist: ipython (>=7.5.0) ; extra == 'dev'
Requires-Dist: m2r (>=0.2.1) ; extra == 'dev'
Requires-Dist: pytest (>=4.3.0) ; extra == 'dev'
Requires-Dist: pytest-cov (==2.6.1) ; extra == 'dev'
Requires-Dist: pytest-raises (>=0.10) ; extra == 'dev'
Requires-Dist: pytest-runner (>=4.4) ; extra == 'dev'
Requires-Dist: Sphinx (<3,>=2.0.0b1) ; extra == 'dev'
Requires-Dist: sphinx-rtd-theme (>=0.4.3) ; extra == 'dev'
Requires-Dist: tox (>=3.5.2) ; extra == 'dev'
Requires-Dist: twine (>=1.13.0) ; extra == 'dev'
Requires-Dist: wheel (>=0.33.1) ; extra == 'dev'
Provides-Extra: interactive
Requires-Dist: altair ; extra == 'interactive'
Requires-Dist: jupyterlab ; extra == 'interactive'
Requires-Dist: matplotlib ; extra == 'interactive'
Provides-Extra: setup
Requires-Dist: pytest-runner ; extra == 'setup'
Provides-Extra: test
Requires-Dist: codecov ; extra == 'test'
Requires-Dist: flake8 ; extra == 'test'
Requires-Dist: black ; extra == 'test'
Requires-Dist: pytest ; extra == 'test'
Requires-Dist: pytest-cov ; extra == 'test'
Requires-Dist: pytest-raises ; extra == 'test'
